yfinance2pg/__init__.py
yfinance2pg/__main__.py
yfinance2pg/args.py
yfinance2pg/config.py
yfinance2pg/db.py
yfinance2pg/download.py
yfinance2pg/help_text.py
yfinance2pg/helpers.py
yfinance2pg/main.py
yfinance2pg/tickers.py
yfinance2pg-1.0.1.dist-info/LICENSE
yfinance2pg-1.0.1.dist-info/METADATA
yfinance2pg-1.0.1.dist-info/WHEEL
yfinance2pg-1.0.1.dist-info/entry_points.txt
yfinance2pg-1.0.1.dist-info/top_level.txt
yfinance2pg-1.0.1.dist-info/RECORD
